rdapy/__init__.py
rdapy/aggregate/__init__.py
rdapy/aggregate/aggregate.py
rdapy/base/__init__.py
rdapy/base/approxequal.py
rdapy/base/constants.py
rdapy/base/data.py
rdapy/base/datasets.py
rdapy/base/distance.py
rdapy/base/ensemble_io.py
rdapy/base/extract.py
rdapy/base/packunpack.py
rdapy/base/readwrite.py
rdapy/base/types.py
rdapy/compactness/__init__.py
rdapy/compactness/compactness.py
rdapy/compactness/discrete_compactness.py
rdapy/compactness/energy.py
rdapy/compactness/features.py
rdapy/compactness/kiwysi.py
rdapy/compactness/smallestenclosingcircle.py
rdapy/compactness/pypoly/__init__.py
rdapy/compactness/pypoly/miniumareaboundingrectangle.py
rdapy/compactness/pypoly/polygonattributes.py
rdapy/compactness/pypoly/polygoncoordinates.py
rdapy/compactness/pypoly/project.py
rdapy/compactness/pypoly/smallestenclosingcircle.py
rdapy/equal/__init__.py
rdapy/equal/population.py
rdapy/graph/__init__.py
rdapy/graph/connected.py
rdapy/graph/embedded.py
rdapy/minority/__init__.py
rdapy/minority/majority_minority.py
rdapy/minority/minority.py
rdapy/partisan/__init__.py
rdapy/partisan/bias.py
rdapy/partisan/geographic.py
rdapy/partisan/method.py
rdapy/partisan/more.py
rdapy/partisan/partisan.py
rdapy/partisan/responsiveness.py
rdapy/partisan/utils.py
rdapy/rate/__init__.py
rdapy/rate/dra_ratings.py
rdapy/rate/normalize.py
rdapy/score/__init__.py
rdapy/score/analyze.py
rdapy/score/analyze_mmd.py
rdapy/score/categories.py
rdapy/splitting/__init__.py
rdapy/splitting/coi.py
rdapy/splitting/county.py
rdapy-3.2.0.dist-info/licenses/LICENSE
rdapy-3.2.0.dist-info/METADATA
rdapy-3.2.0.dist-info/WHEEL
rdapy-3.2.0.dist-info/top_level.txt
rdapy-3.2.0.dist-info/RECORD
