Metadata-Version: 2.4
Name: rdapy
Version: 3.2.0
Summary: Redistricting analytics in Python
Home-page: https://github.com/dra2020/rdapy
Author: alecramsay
Author-email: Alec Ramsay <alec@davesredistricting.org>
License: MIT
Project-URL: Homepage, https://github.com/dra2020/rdapy
Project-URL: Bug Tracker, https://github.com/dra2020/rdapy/issues
Classifier: Programming Language :: Python :: 3
Classifier: License :: OSI Approved :: MIT License
Classifier: Operating System :: OS Independent
Requires-Python: >=3.10
License-File: LICENSE
Requires-Dist: Fiona
Requires-Dist: geographiclib
Requires-Dist: geopandas
Requires-Dist: libpysal
Requires-Dist: nptyping
Requires-Dist: numpy
Requires-Dist: pandas
Requires-Dist: pyproj
Requires-Dist: pytest
Requires-Dist: scipy
Requires-Dist: shapely
Dynamic: author
Dynamic: home-page
Dynamic: license
Dynamic: license-file
Dynamic: requires-dist
